opengl_utils/__init__.py
opengl_utils/code1.py
opengl_utils/code2.py
opengl_utils/exam1.py
opengl_utils/exam2.py
opengl_utils-0.1.6.dist-info/METADATA
opengl_utils-0.1.6.dist-info/WHEEL
opengl_utils-0.1.6.dist-info/top_level.txt
opengl_utils-0.1.6.dist-info/RECORD
