Metadata-Version: 2.4
Name: opengl_utils
Version: 0.1.6
Summary: A utility package for OpenGL
Home-page: https://github.com/johndoe/opengl_utils
Author: John Machanzy
Author-email: jphn@machanzy.com
Classifier: Programming Language :: Python :: 3
Classifier: License :: OSI Approved :: MIT License
Classifier: Operating System :: OS Independent
Requires-Python: >=3.6
Dynamic: author
Dynamic: author-email
Dynamic: classifier
Dynamic: description
Dynamic: description-content-type
Dynamic: home-page
Dynamic: requires-python
Dynamic: summary
